vpc_img_inst/__init__.py
vpc_img_inst/config_builder.py
vpc_img_inst/constants.py
vpc_img_inst/defaults.yaml
vpc_img_inst/main.py
vpc_img_inst/utils.py
vpc_img_inst/bin/__init__.py
vpc_img_inst/bin/vpc_img_inst.py
vpc_img_inst/config_modules/__init__.py
vpc_img_inst/config_modules/apikey_config.py
vpc_img_inst/config_modules/delete_resources.py
vpc_img_inst/config_modules/endpoint_config.py
vpc_img_inst/config_modules/image_config.py
vpc_img_inst/config_modules/image_create.py
vpc_img_inst/config_modules/install_feature.py
vpc_img_inst/config_modules/ip_config.py
vpc_img_inst/config_modules/ssh_config.py
vpc_img_inst/config_modules/vpc_config.py
vpc_img_inst/config_modules/vsi_config.py
vpc_img_inst/installation_scripts/cuda/install_cuda_rhel.sh
vpc_img_inst/installation_scripts/cuda/install_cuda_ubuntu.sh
vpc_img_inst/installation_scripts/docker/install_docker_rhel.sh
vpc_img_inst/installation_scripts/docker/install_docker_ubuntu.sh
vpc_img_inst/installation_scripts/ray/install_ray_ubuntu.sh
vpc_img_inst-1.0.0b7.dist-info/LICENSE
vpc_img_inst-1.0.0b7.dist-info/METADATA
vpc_img_inst-1.0.0b7.dist-info/WHEEL
vpc_img_inst-1.0.0b7.dist-info/entry_points.txt
vpc_img_inst-1.0.0b7.dist-info/top_level.txt
vpc_img_inst-1.0.0b7.dist-info/RECORD
