Metadata-Version: 2.1
Name: vpc-img-inst
Version: 1.0.0b7
Summary: vpc-img-inst is a lightweight script for quick-and-dirty generation of custom VSI images by installing features (software bundles) on base images.
Home-page: https://github.com/IBM/vpc-img-inst
Author: Omer-J-Cohen
Author-email: omer.cohen@ibm.com
Requires-Python: >=3.6
License-File: LICENSE
Requires-Dist: click (==8.0.4)
Requires-Dist: ibm-cloud-sdk-core (==3.16.0)
Requires-Dist: ibm-platform-services (==0.27.0)
Requires-Dist: ibm-vpc (==0.12.0)
Requires-Dist: ibm-watson (==6.1.0)
Requires-Dist: inquirer (==2.10.1)
Requires-Dist: paramiko (==2.11.0)
Requires-Dist: PyYAML (==6.0)
Requires-Dist: setuptools (==63.2.0)
